MANIFEST.in
README.md
setup.py
./ddb/cli.c
./ddb/engine.c
./ddb/interactive.c
./ddb/version.c
./ddb/configuration/column.c
./ddb/configuration/database.c
./ddb/configuration/table.c
./ddb/file_io/locking.c
./ddb/functions/functions.c
./ddb/lexer/language.c
./ddb/lexer/lexer.c
./ddb/lexer/tokenize.c
./ddb/meta/meta.c
./ddb/methods/database_show_errors.c
./ddb/methods/database_use.c
./ddb/methods/record_core.c
./ddb/methods/record_delete.c
./ddb/methods/record_insert.c
./ddb/methods/record_select.c
./ddb/methods/record_update.c
./ddb/methods/record_upsert.c
./ddb/methods/system_begin.c
./ddb/methods/system_commit.c
./ddb/methods/system_rollback.c
./ddb/methods/system_set.c
./ddb/methods/system_show_columns.c
./ddb/methods/system_show_output_modules.c
./ddb/methods/system_show_tables.c
./ddb/methods/system_show_variables.c
./ddb/methods/table_create.c
./ddb/methods/table_describe.c
./ddb/methods/table_drop.c
./ddb/methods/table_update.c
./ddb/output/factory.c
./ddb/output/factory_json.c
./ddb/output/factory_term.c
./ddb/output/factory_xml.c
./ddb/output/factory_yaml.c
ddb/__init__.py
ddb/cli.c
ddb/engine.c
ddb/interactive.c
ddb/version.c
ddb/version.py
ddb.egg-info/PKG-INFO
ddb.egg-info/SOURCES.txt
ddb.egg-info/dependency_links.txt
ddb.egg-info/entry_points.txt
ddb.egg-info/top_level.txt
ddb/configuration/__init__.py
ddb/configuration/column.c
ddb/configuration/database.c
ddb/configuration/table.c
ddb/file_io/__init__.py
ddb/file_io/locking.c
ddb/functions/__init__.py
ddb/functions/functions.c
ddb/lexer/__init__.py
ddb/lexer/language.c
ddb/lexer/lexer.c
ddb/lexer/tokenize.c
ddb/meta/__init__.py
ddb/meta/meta.c
ddb/methods/__init__.py
ddb/methods/database_show_errors.c
ddb/methods/database_use.c
ddb/methods/record_core.c
ddb/methods/record_delete.c
ddb/methods/record_insert.c
ddb/methods/record_select.c
ddb/methods/record_update.c
ddb/methods/record_upsert.c
ddb/methods/system_begin.c
ddb/methods/system_commit.c
ddb/methods/system_rollback.c
ddb/methods/system_set.c
ddb/methods/system_show_columns.c
ddb/methods/system_show_output_modules.c
ddb/methods/system_show_tables.c
