Metadata-Version: 2.1
Name: ddb
Version: 1.4.169
Summary: A serviceless sql interface for flat files written in cython
Home-page: https://github.com/chris17453/ddb/
Author: Charles Watkins
Author-email: chris17453@gmail.com
License: Creative Commons Attribution-Noncommercial-Share Alike license
Platform: UNKNOWN
Classifier: Programming Language :: Python :: 2.7
Classifier: Development Status :: 3 - Alpha
Classifier: Operating System :: OS Independent
